Metadata-Version: 2.1
Name: dbactor
Version: 0.0.3
Summary: DBActor: ORM helper and alternative
Home-page: http://github.com/jackschultz/dbactor
Author: Jack Schultz
Author-email: jackschultz23@gmail.com
License: MIT
Platform: UNKNOWN
Provides-Extra: jinjasql
Provides-Extra: sqlalchemy
Provides-Extra: pandas
Provides-Extra: all
